pytest_dynamodb/__init__.py
pytest_dynamodb/config.py
pytest_dynamodb/plugin.py
pytest_dynamodb/py.typed
pytest_dynamodb/factories/__init__.py
pytest_dynamodb/factories/client.py
pytest_dynamodb/factories/noprocess.py
pytest_dynamodb/factories/process.py
pytest_dynamodb-2.5.1.dist-info/licenses/AUTHORS.rst
pytest_dynamodb-2.5.1.dist-info/licenses/COPYING
pytest_dynamodb-2.5.1.dist-info/licenses/COPYING.lesser
pytest_dynamodb-2.5.1.dist-info/METADATA
pytest_dynamodb-2.5.1.dist-info/WHEEL
pytest_dynamodb-2.5.1.dist-info/entry_points.txt
pytest_dynamodb-2.5.1.dist-info/top_level.txt
pytest_dynamodb-2.5.1.dist-info/zip-safe
pytest_dynamodb-2.5.1.dist-info/RECORD
