Metadata-Version: 2.4
Name: pytest-dynamodb
Version: 2.5.1
Summary: DynamoDB fixtures for pytest
Author-email: Grzegorz Śliwiński <fizyk+pypi@fizyk.dev>
License:                    GNU LESSER GENERAL PUBLIC LICENSE
Project-URL: Source, https://github.com/dbfixtures/pytest-dynamodb
Project-URL: Bug Tracker, https://github.com/dbfixtures/pytest-dynamodb/issues
Project-URL: Changelog, https://github.com/dbfixtures/pytest-dynamodb/blob/v2.5.1/CHANGES.rst
Keywords: tests,pytest,fixture,dynamodb,aws,boto
Classifier: Development Status :: 5 - Production/Stable
Classifier: Environment :: Web Environment
Classifier: Intended Audience :: Developers
Classifier: License :: OSI Approved :: GNU Lesser General Public License v3 or later (LGPLv3+)
Classifier: Natural Language :: English
Classifier: Operating System :: OS Independent
Classifier: Programming Language :: Python
Classifier: Programming Language :: Python :: 3
Classifier: Programming Language :: Python :: 3.9
Classifier: Programming Language :: Python :: 3.10
Classifier: Programming Language :: Python :: 3.11
Classifier: Programming Language :: Python :: 3.12
Classifier: Programming Language :: Python :: 3.13
Classifier: Programming Language :: Python :: 3 :: Only
Classifier: Topic :: Software Development :: Libraries :: Python Modules
Classifier: Topic :: Software Development :: Testing
Classifier: Framework :: Pytest
Requires-Python: >=3.9
License-File: COPYING
License-File: COPYING.lesser
License-File: AUTHORS.rst
Requires-Dist: pytest
Requires-Dist: port-for>=0.7.1
Requires-Dist: mirakuru
Requires-Dist: boto3
Requires-Dist: boto3-stubs[dynamodb]
Dynamic: license-file
